globgroups/.gitignore
globgroups/__init__.py
globgroups/__main__.py
globgroups/_parse.py
globgroups/_version.py
globgroups/py.typed
globgroups-0.1.0b3.dist-info/LICENSE.txt
globgroups-0.1.0b3.dist-info/METADATA
globgroups-0.1.0b3.dist-info/WHEEL
globgroups-0.1.0b3.dist-info/top_level.txt
globgroups-0.1.0b3.dist-info/RECORD
